convert_jupyter/__init__.py
convert_jupyter/__main__.py
convert_jupyter/clean.py
convert_jupyter/code.py
convert_jupyter/constans.py
convert_jupyter-1.0.3.dist-info/METADATA
convert_jupyter-1.0.3.dist-info/WHEEL
convert_jupyter-1.0.3.dist-info/licenses/LICENSE.md
convert_jupyter-1.0.3.dist-info/RECORD
