Metadata-Version: 2.1
Name: convert-jupyter
Version: 1.0.3
Summary: Package help convert jupyter files. It let convert py to jupyter file and vice versa, and clean jupyter output. Useful to exclude git conflicts
Project-URL: Homepage, https://github.com/chwilko/convert_jupyter
Author-email: Bartłomiej Chwiłkowski <bartekchwilkowski@gmail.com>
License-File: LICENSE.md
Classifier: License :: OSI Approved :: MIT License
Classifier: Operating System :: OS Independent
Classifier: Programming Language :: Python :: 3
Requires-Python: >=3.7
